RES/SXH128.py
RES/SXH256.py
RES/SXH512.py
RES/__init__.py
RES/cooc_sc.py
RES/grid_cipher.py
RES/key_block_cipher.py
RES/main.py
RES/res_random.py
RES/shuffle.py
REScrypt-0.0.2.dist-info/METADATA
REScrypt-0.0.2.dist-info/WHEEL
REScrypt-0.0.2.dist-info/top_level.txt
REScrypt-0.0.2.dist-info/RECORD
