Metadata-Version: 2.1
Name: REScrypt
Version: 0.0.2
Summary: Randomized Encryption System
Author: HarbingerOfFire
Author-email: harbingeroffire@proton.me
Keywords: python,random,SXH,RES,Encryption,cryptography
